volumouse/__init__.py
volumouse/__version__.py
volumouse/volumouse.py
volumouse/icons/__init__.py
volumouse/temp/__init__.py
volumouse/test/__init__.py
volumouse/test/test.py
volumouse-0.0.9.dist-info/LICENSE
volumouse-0.0.9.dist-info/METADATA
volumouse-0.0.9.dist-info/WHEEL
volumouse-0.0.9.dist-info/entry_points.txt
volumouse-0.0.9.dist-info/top_level.txt
volumouse-0.0.9.dist-info/RECORD
