Metadata-Version: 2.1
Name: volumouse
Version: 0.0.9
Summary: A Python 3 program that allows you to change the volume with the mouse wheel using it at the four corners of the screen.
Author-email: Pzim-devdata <contact@pzim.fr>
Project-URL: Homepage, https://github.com/pzim-devdata/volumouse
Project-URL: Bug Tracker, https://github.com/pzim-devdata/volumouse/issues
Keywords: volume,mouse,screen
Classifier: Programming Language :: Python :: 3
Classifier: License :: OSI Approved :: MIT License
Classifier: Operating System :: OS Independent
Requires-Python: >=3.7
License-File: LICENSE
Requires-Dist: python3-xlib
